powersddp/__init__.py
powersddp/core/__init__.py
powersddp/core/api.py
powersddp/core/system.py
powersddp/utils/__init__.py
powersddp/utils/_solver.py
powersddp/utils/_yml.py
powersddp-0.0.3.dist-info/LICENSE.md
powersddp-0.0.3.dist-info/WHEEL
powersddp-0.0.3.dist-info/METADATA
powersddp-0.0.3.dist-info/RECORD
