Metadata-Version: 2.1
Name: powersddp
Version: 0.0.3
Summary: A Stochastic Dual Dynamic Programmimg library to solve economical dispach of power systems.
Home-page: https://github.com/ettoreaquino/powersddp.git
Author: Ettore Aquino
Author-email: ettore@ettoreaquino.com
Requires-Python: >=3.7,<4.0
Classifier: Programming Language :: Python :: 3
Classifier: Programming Language :: Python :: 3.7
Classifier: Programming Language :: Python :: 3.8
Classifier: Programming Language :: Python :: 3.9
Requires-Dist: PyYAML (>=5.4.1,<6.0.0)
Requires-Dist: cvxopt (>=1.2.6,<2.0.0)
Requires-Dist: numpy (>=1.21.1,<2.0.0)
Requires-Dist: pandas (>=1.3.2,<2.0.0)
Requires-Dist: plotly (>=5.2.1,<6.0.0)
Project-URL: Repository, https://github.com/ettoreaquino/powersddp.git
